RTIMU.cpython-34m.so
RTIMULib-7.2.1b1.dist-info/RECORD
RTIMULib-7.2.1b1.dist-info/DESCRIPTION.rst
RTIMULib-7.2.1b1.dist-info/metadata.json
RTIMULib-7.2.1b1.dist-info/top_level.txt
RTIMULib-7.2.1b1.dist-info/METADATA
RTIMULib-7.2.1b1.dist-info/WHEEL
