Metadata-Version: 2.0
Name: RTIMULib
Version: 7.2.1b1
Summary: richards-tech IMU Sensor Fusion Library
Home-page: UNKNOWN
Author: UNKNOWN
Author-email: UNKNOWN
License: UNKNOWN
Platform: UNKNOWN
